cpu.v
module alu (
  input clk,
  input [2:0] funct3,
  input [31:0] x,
  input [31:0] y,
  input alt,
  output reg [31:0] out
);
  always @(posedge clk) begin
    case (funct3) 
      3'b000: begin  // ADDI
        out <= alt ? (x - y) : (x + y);
      end
      3'b001: begin  // SLL
        out <= x << y[4:0];
      end
      3'b010: begin  // SLT
        out <= {31'b0, $signed(x) < $signed(y)};
      end
      3'b011: begin  // SLTU
        out <= {31'b0, x < y};
      end
      3'b100: begin  // XOR
        out <= x ^ y;
      end
      3'b101: begin  // SRL
        out <= alt ? (x >>> y[4:0]) : (x >> y[4:0]);
      end
      3'b110: begin  // OR
        out <= x | y;
      end
      3'b111: begin  // AND
        out <= x & y;
      end
    endcase
  end
endmodule

module cond (
  input clk, 
  input [2:0] funct3,
  input [31:0] x,
  input [31:0] y,
  output reg out
);
  always @(posedge clk) begin
    case (funct3) 
      3'b000: begin  // BEQ
        out <= x == y;
      end
      3'b001: begin  // BNE
        out <= x != y;
      end
      3'b100: begin  // BLT
        out <= $signed(x) < $signed(y);
      end
      3'b101: begin  // BGE
        out <= $signed(x) >= $signed(y);
      end
      3'b110: begin  // BLTU
        out <= x < y;
      end
      3'b111: begin  // BGEU
        out <= x >= y;
      end
    endcase
  end
endmodule

module ram (
  input clk,
  input [13:0] i_addr,
  output reg [31:0] i_data,
  input [13:0] d_addr,
  output reg [31:0] d_data,
  input [31:0] dw_data,
  input [1:0] dw_size);

  // 16 KB
  reg [31:0] mem [0:4095];
  wire [31:0] dt_data = mem[d_addr[13:2]];

  always @(posedge clk) begin
    // always aligned for instruction fetch
    i_data <= mem[i_addr[13:2]];
    // misaligned data, but it's filled with 0s
    // support some unaligned loads, but can't break word boundary
    d_data <=
      d_addr[1] ? (d_addr[0] ? (dt_data >> 24) : (dt_data >> 16))
                : (d_addr[0] ? (dt_data >> 8) : dt_data);
    // 2'b01 = 8-bit
    // 2'b10 = 16-bit
    // 2'b11 = 32-bit
    // again, can't break word boundary
    case (dw_size)
      2'b11: mem[d_addr[13:2]] <= dw_data;
      2'b10: mem[d_addr[13:2]] <= 
        d_addr[1] ? {dw_data[15:0], dt_data[15:0]} : 
                    {dt_data[31:16], dw_data[15:0]};
      2'b01: mem[d_addr[13:2]] <= 
        d_addr[1] ?
          (d_addr[0] ? {dw_data[7:0], dt_data[23:0]} : {dt_data[31:24], dw_data[7:0], dt_data[15:0]}) :
          (d_addr[0] ? {dt_data[31:16], dw_data[7:0], dt_data[7:0]} : {dt_data[31:8], dw_data[7:0]});
    endcase
  end
endmodule

// twitchcore is a low performance RISC-V processor
module twitchcore (
  input clk, resetn,
  output reg trap,
  output reg [31:0] pc
);

  //wire [13:0] i_addr = pc[13:0];
  reg [13:0] i_addr;
  wire [31:0] i_data;
  reg [13:0] d_addr;
  wire [31:0] d_data;
  reg [31:0] dw_data;
  reg [1:0] dw_size;
  ram r (
    .clk (clk),
    .i_data (i_data),
    .i_addr (i_addr),
    .d_data (d_data),
    .d_addr (d_addr),
    .dw_data (dw_data),
    .dw_size (dw_size)
  );

  reg [31:0] regs [0:31];
  reg [4:0] rd;

  reg [31:0] vs1;
  reg [31:0] vs2;
  reg [31:0] vpc;

  // Instruction decode and register fetch
  wire [6:0] opcode = i_data[6:0];
  wire [2:0] funct3 = i_data[14:12];
  wire [6:0] funct7 = i_data[31:25];
  wire [4:0] rs1 = i_data[19:15];
  wire [4:0] rs2 = i_data[24:20];
  wire [31:0] imm_i = {{20{i_data[31]}}, i_data[31:20]};
  wire [31:0] imm_s = {{20{i_data[31]}}, i_data[31:25], i_data[11:7]};
  wire [31:0] imm_b = {{19{i_data[31]}}, i_data[31], i_data[7], i_data[30:25], i_data[11:8], 1'b0};
  wire [31:0] imm_u = {i_data[31:12], 12'b0};
  wire [31:0] imm_j = {{11{i_data[31]}}, i_data[31], i_data[19:12], i_data[20], i_data[30:21], 1'b0};

  reg [31:0] alu_left;
  reg [31:0] alu_imm;
  reg [2:0] alu_func;
  reg alu_alt;

  wire [31:0] pend;
  reg [2:0] funct3_saved;
  wire cond_out;
  reg [1:0] update_pc;  // 2'b00: don't update, 2'b01: update always, 2'b10: update cond
  reg reg_writeback;

  wire pend_is_new_pc = update_pc[0] || (update_pc[1] && cond_out);
  reg do_load;
  reg do_store;

  reg [6:0] step;

  alu a (
    .clk (clk),
    .funct3 (alu_func),
    .x (alu_left),
    .y (alu_imm),
    .alt (alu_alt),
    .out (pend)
  );

  cond c (
    .clk (clk),
    .funct3 (funct3_saved),
    .x (vs1),
    .y (vs2),
    .out (cond_out)
  );

  /*parameter SZ = 4;
  parameter LOGCNT = 5;
  parameter BITS = 18;
  reg [2:0] risk_func;
  reg [4:0] risk_reg;
  reg [10+LOGCNT-1:0] risk_addr;
  reg [10+LOGCNT-2:0] risk_stride_x;
  reg [10+LOGCNT-2:0] risk_stride_y;
  wire [BITS*SZ*SZ-1:0] risk_reg_view;
  risk #(SZ, LOGCNT, BITS) ri (
    .clk (clk),
    .risk_func (risk_func),
    .risk_reg (risk_reg),
    .risk_addr (risk_addr),
    .risk_stride_x (risk_stride_x),
    .risk_stride_y (risk_stride_y),
    .reg_view (risk_reg_view)
  );*/

  integer i;
  always @(posedge clk) begin
    step <= step << 1;
    if (resetn) begin
      pc <= 32'h80000000;
      for (i=0; i<32; i=i+1) regs[i] <= 0;
      step <= 'b1;
      trap <= 1'b0;
    end

    // *** Instruction Fetch ***
    i_addr <= pc[13:0];
    // it sets i_data here from pc

    // *** Instruction decode and register fetch ***
    vs1 <= regs[rs1];
    vs2 <= regs[rs2];
    vpc <= pc;
    rd <= i_data[11:7];
    funct3_saved <= funct3;

    alu_func <= 3'b000;
    alu_left <= vs1;
    alu_alt <= 1'b0;
    update_pc <= 2'b00;
    reg_writeback <= 1'b0;
    do_load <= 1'b0;
    do_store <= 1'b0;
    case (opcode)
      7'b0110111: begin // LUI
        alu_imm <= imm_u;
        alu_left <= 32'b0;
        reg_writeback <= 1'b1;
      end
      7'b0000011: begin // LOAD
        alu_imm <= imm_i;
        reg_writeback <= 1'b1;
        do_load <= 1'b1;
      end
      7'b0100011: begin // STORE
        alu_imm <= imm_s;
        do_store <= 1'b1;
      end

      7'b0010111: begin // AUIPC
        alu_imm <= imm_u;
        alu_left <= pc;
        reg_writeback <= 1'b1;
      end
      7'b1100011: begin // BRANCH
        alu_imm <= imm_b;
        alu_left <= pc;
        update_pc <= 2'b10;
      end
      7'b1101111: begin // JAL
        alu_imm <= imm_j;
        alu_left <= pc;
        update_pc <= 2'b01;
        reg_writeback <= 1'b1;
      end
      7'b1100111: begin // JALR
        alu_imm <= imm_i;
        update_pc <= 2'b01;
        reg_writeback <= 1'b1;
      end

      7'b0010011: begin // IMM
        alu_imm <= imm_i;
        alu_func <= funct3;
        alu_alt <= (funct7 == 7'b0100000 && funct3 == 3'b101);
        reg_writeback <= 1'b1;
      end
      7'b0110011: begin // OP
        alu_imm <= regs[rs2];
        alu_func <= funct3;
        alu_alt <= (funct7 == 7'b0100000);
        reg_writeback <= 1'b1;
      end

      /*7'b1111111: begin // RISK
        risk_func <= funct3;
        risk_addr <= regs[rs1];
        risk_stride_x <= regs[rs2][31:16];
        risk_stride_y <= regs[rs2][15:0];
        risk_reg <= i_data[11:7];
        // 9 DWORDs
        case (funct7) 
          7'b0000000: alu_imm <= risk_reg_view[31:0];
          7'b0000001: alu_imm <= risk_reg_view[63:32];
          7'b0000010: alu_imm <= risk_reg_view[95:64];
          7'b0000011: alu_imm <= risk_reg_view[127:96];
          7'b0000100: alu_imm <= risk_reg_view[159:128];
          7'b0000101: alu_imm <= risk_reg_view[191:160];
          7'b0000110: alu_imm <= risk_reg_view[223:192];
          7'b0000111: alu_imm <= risk_reg_view[255:224];
          7'b0001000: alu_imm <= risk_reg_view[288:256];
        endcase
        alu_left <= 32'b0;
        reg_writeback <= 1'b1;
      end*/

      7'b1110011: begin // SYSTEM
        trap <= regs[3] > 0;
      end
    endcase

    // *** Execute (happens above in arith and cond) ***
    // it sets pend and cond_out here

    // *** Memory access ***
    // this sets d_data based on pend
    if (step[5] == 1'b1) begin
      d_addr <= pend[13:0];
      if (do_store) begin
        dw_data <= vs2;
        dw_size <= (funct3_saved[1:0] + 1);
      end
    end
    
    // *** Register Writeback ***
    if (step[6] == 1'b1) begin
      pc <= pend_is_new_pc ? pend : (vpc + 4);
      if (reg_writeback && rd != 5'b00000) begin
        if (do_load) begin
          case (funct3_saved)
            3'b000: regs[rd] <= {{24{d_data[7]}}, d_data[7:0]};
            3'b001: regs[rd] <= {{16{d_data[15]}}, d_data[15:0]};
            3'b010: regs[rd] <= d_data;
            3'b100: regs[rd] <= {24'b0, d_data[7:0]};
            3'b101: regs[rd] <= {16'b0, d_data[15:0]};
          endcase
        end else begin
          regs[rd] <= (pend_is_new_pc ? (vpc + 4) : pend);
        end
      end
      step <= 'b1;
      dw_size <= 2'b00;
    end
  end

endmodule

testbench.sv
`define hdl_path_regf c.regs
module testbench;

  reg clk;
  reg resetn;
  wire trap;
  reg [7:0] cnt;

  twitchcore c (
    .clk (clk),
    .resetn (resetn),
    .trap (trap)
  );

  initial begin
    string firmware;
    clk = 0;
    cnt = 0;
    // put core to reset while initializing ram
    resetn = 0;

    $display("programming the mem");
    if ($value$plusargs("firmware=%s", firmware)) begin
        $display($sformatf("Using %s as firmware", firmware));
    end else begin
        $display($sformatf("Expecting a command line argument %s", firmware), "ERROR");
        $finish;
    end
    $readmemh(firmware, c.r.mem);

    $display("doing work", cnt);
    @(posedge clk);
    resetn = 1;
  end

  always
    #5 clk = !clk;

  always @(posedge clk) begin
    cnt <= cnt + 1;
    resetn <= 0;
  end



  always @(posedge clk) begin
    if (c.step[6] == 1'b1) begin
      $display("%b: %h %d pc:%h -- opcode:%b -- func:%h alt:%d left:%h imm:%h pend:%h d_addr:%h d_data:%h c.rs1:%h c.rs2:%h c.rd:%h",
        c.step, c.i_data, c.resetn, c.pc, c.opcode, c.alu_func, c.alu_alt, c.alu_left, c.alu_imm, c.pend, c.d_addr, c.d_data, c.rs1, c.rs2, c.rd);
    end
  end

  always @(posedge trap) begin
    $display("TRAP", c.regs[3]);
    $finish;
  end

  initial begin
    int char_0, char_1, char_2, char_3;
    $dumpfile("waves.vcd");
    $dumpvars(0,testbench);
    #50000
    $display("no more work ", cnt);
    // At the end of risc-v test, we should see OK\n or
    // Err\n in registers a0-a3 ()
    char_0 = `hdl_path_regf[10];
    char_1 = `hdl_path_regf[11];
    char_2 = `hdl_path_regf[12];
    char_3 = `hdl_path_regf[13];
    $display($sformatf("RISC-V TEST Result: %s%s%s%s", char_0, char_1, char_2, char_3));
    $finish;
  end
endmodule

waves.vcd
$date
	Sun May 15 13:32:03 2022
$end
$version
	Icarus Verilog
$end
$timescale
	1s
$end
$scope module testbench $end
$var wire 1 ! trap $end
$var reg 1 " clk $end
$var reg 8 # cnt [7:0] $end
$var reg 1 $ resetn $end
$scope module c $end
$var wire 1 " clk $end
$var wire 1 % pend_is_new_pc $end
$var wire 1 $ resetn $end
$var wire 5 & rs2 [4:0] $end
$var wire 5 ' rs1 [4:0] $end
$var wire 32 ( pend [31:0] $end
$var wire 7 ) opcode [6:0] $end
$var wire 32 * imm_u [31:0] $end
$var wire 32 + imm_s [31:0] $end
$var wire 32 , imm_j [31:0] $end
$var wire 32 - imm_i [31:0] $end
$var wire 32 . imm_b [31:0] $end
$var wire 32 / i_data [31:0] $end
$var wire 7 0 funct7 [6:0] $end
$var wire 3 1 funct3 [2:0] $end
$var wire 32 2 d_data [31:0] $end
$var wire 1 3 cond_out $end
$var reg 1 4 alu_alt $end
$var reg 3 5 alu_func [2:0] $end
$var reg 32 6 alu_imm [31:0] $end
$var reg 32 7 alu_left [31:0] $end
$var reg 14 8 d_addr [13:0] $end
$var reg 1 9 do_load $end
$var reg 1 : do_store $end
$var reg 32 ; dw_data [31:0] $end
$var reg 2 < dw_size [1:0] $end
$var reg 3 = funct3_saved [2:0] $end
$var reg 14 > i_addr [13:0] $end
$var reg 32 ? pc [31:0] $end
$var reg 5 @ rd [4:0] $end
$var reg 1 A reg_writeback $end
$var reg 7 B step [6:0] $end
$var reg 1 ! trap $end
$var reg 2 C update_pc [1:0] $end
$var reg 32 D vpc [31:0] $end
$var reg 32 E vs1 [31:0] $end
$var reg 32 F vs2 [31:0] $end
$var integer 32 G i [31:0] $end
$scope module a $end
$var wire 1 4 alt $end
$var wire 1 " clk $end
$var wire 3 H funct3 [2:0] $end
$var wire 32 I x [31:0] $end
$var wire 32 J y [31:0] $end
$var reg 32 K out [31:0] $end
$upscope $end
$scope module c $end
$var wire 1 " clk $end
$var wire 3 L funct3 [2:0] $end
$var wire 32 M x [31:0] $end
$var wire 32 N y [31:0] $end
$var reg 1 3 out $end
$upscope $end
$scope module r $end
$var wire 1 " clk $end
$var wire 14 O d_addr [13:0] $end
$var wire 32 P dt_data [31:0] $end
$var wire 32 Q dw_data [31:0] $end
$var wire 2 R dw_size [1:0] $end
$var wire 14 S i_addr [13:0] $end
$var reg 32 T d_data [31:0] $end
$var reg 32 U i_data [31:0] $end
$upscope $end
$upscope $end
$scope begin $unm_blk_1 $end
$upscope $end
$scope begin $unm_blk_8 $end
$var integer 32 V char_0 [31:0] $end
$var integer 32 W char_1 [31:0] $end
$var integer 32 X char_2 [31:0] $end
$var integer 32 Y char_3 [31:0] $end
$upscope $end
$upscope $end
$enddefinitions $end
#0
$dumpvars
b0 Y
b0 X
b0 W
b0 V
bx U
bx T
bx S
bx R
bx Q
bx P
bx O
bx N
bx M
bx L
bx K
bx J
bx I
bx H
bx G
bx F
bx E
bx D
bx C
bx B
xA
bx @
bx ?
bx >
bx =
bx <
bx ;
x:
x9
bx 8
bx 7
bx 6
bx 5
x4
x3
bx 2
bx 1
bx 0
bx /
bx0 .
bx -
bx0 ,
bx +
bx000000000000 *
bx )
bx (
bx '
bx &
x%
0$
b0 #
0"
x!
$end
#5
0%
0:
09
0A
b0 C
04
b0 5
b0 H
0!
b10000000000000000000000000000000 ?
b1 B
b1 #
b100000 G
0$
1"
#10
0"
#15
b10 #
b10000000000000000000000000000000 D
b0 >
b0 S
b10 B
1"
#20
0"
#25
b11111111111101000000110110100000 ,
b11011010000101000000000000000000 *
b11111111111111111111110110111110 .
b11111111111111111111110110111111 +
b11111111111111111111110110100001 -
b1 &
b1000 '
b1101101 0
b0 1
b101011 )
b11011010000101000000111110101011 /
b11011010000101000000111110101011 U
b100 B
b11 #
1"
#30
0"
#35
b100 #
b0 =
b0 L
b11111 @
b0 F
b0 N
b0 E
b0 M
b1000 B
1"
#40
0"
#45
13
b0 7
b0 I
b10000 B
b101 #
1"
#50
0"
#55
b110 #
b100000 B
1"
#60
0"
#65
b1000000 B
b111 #
1"
#70
0"
#75
b1000 #
b0 <
b0 R
b10000000000000000000000000000100 ?
b1 B
1"
#80
0"
#85
b10000000000000000000000000000100 D
b100 >
b100 S
b10 B
b1001 #
1"
#90
0"
#95
b11111111111110000001111000001010 ,
b11100000101110000001000000000000 *
b11111111111111111111111000000110 .
b11111111111111111111111000000111 +
b11111111111111111111111000001011 -
b1011 &
b10000 '
b1110000 0
b1 1
b1010010 )
b1010 #
b100 B
b11100000101110000001001111010010 /
b11100000101110000001001111010010 U
1"
#100
0"
#105
b1 =
b1 L
b111 @
b1000 B
b1011 #
1"
#110
0"
#115
b1100 #
b10000 B
03
1"
#120
0"
#125
b100000 B
b1101 #
1"
#130
0"
#135
b1110 #
b1000000 B
1"
#140
0"
#145
b10000000000000000000000000001000 ?
b1 B
b1111 #
1"
#150
0"
#155
b10000 #
b10000000000000000000000000001000 D
b1000 >
b1000 S
b10 B
1"
#160
0"
#165
b11111111111101101001111111101000 ,
b11111110100101101001000000000000 *
b11111111111111111111111111111110 .
b11111111111111111111111111111111 +
b11111111111111111111111111101001 -
b1001 &
b1101 '
b1111111 0
b100100 )
b11111110100101101001111110100100 /
b11111110100101101001111110100100 U
b100 B
b10001 #
1"
#170
0"
#175
b10010 #
b11111 @
b1000 B
1"
#180
0"
#185
b10000 B
b10011 #
1"
#190
0"
#195
b10100 #
b100000 B
1"
#200
0"
#205
b1000000 B
b10101 #
1"
#210
0"
#215
b10110 #
b10000000000000000000000000001100 ?
b1 B
1"
#220
0"
#225
b10000000000000000000000000001100 D
b1100 >
b1100 S
b10 B
b10111 #
1"
#230
0"
#235
b11101111110011001000 ,
b1001100100111101111000000000000 *
b10011001110 .
b10011001110 +
b10011001001 -
b11101 '
b100110 0
b111 1
b110110 )
b11000 #
b100 B
b1001100100111101111011100110110 /
b1001100100111101111011100110110 U
1"
#240
0"
#245
b111 =
b111 L
b1110 @
b1000 B
b11001 #
1"
#250
0"
#255
b11010 #
b10000 B
13
1"
#260
0"
#265
b100000 B
b11011 #
1"
#270
0"
#275
b11100 #
b1000000 B
1"
#280
0"
#285
b10000000000000000000000000010000 ?
b1 B
b11101 #
1"
#290
0"
#295
b11110 #
b10000000000000000000000000010000 D
b10000 >
b10000 S
b10 B
1"
#300
0"
#305
b1010000010011010110 ,
b1001101011001010000000000000000 *
b110011000100 .
b10011000101 +
b10011010110 -
b10110 &
b1010 '
b0 1
b110111 )
b1001101011001010000001010110111 /
b1001101011001010000001010110111 U
b100 B
b11111 #
1"
#310
0"
#315
b100000 #
1A
b1001101011001010000000000000000 6
b1001101011001010000000000000000 J
b0 =
b0 L
b101 @
b1000 B
1"
#320
0"
#325
b1001101011001010000000000000000 (
b1001101011001010000000000000000 K
1A
b10000 B
b100001 #
1"
#330
0"
#335
b100010 #
1A
b100000 B
1"
#340
0"
#345
b11011010000101000000111110101011 P
b0 8
b0 O
1A
b1000000 B
b100011 #
1"
#350
0"
#355
b100100 #
b10000000000000000000000000010100 ?
1A
b1 B
b11011010000101000000111110101011 2
b11011010000101000000111110101011 T
1"
#360
0"
#365
1A
b10000000000000000000000000010100 D
b10100 >
b10100 S
b10 B
b100101 #
1"
#370
0"
#375
b11111111111100001101000011000110 ,
b10001100011000001101000000000000 *
b11111111111111111111100011000010 .
b11111111111111111111100011000011 +
b11111111111111111111100011000110 -
b110 &
b1 '
b1000110 0
b101 1
b1110000 )
b100110 #
1A
b100 B
b10001100011000001101000111110000 /
b10001100011000001101000111110000 U
1"
#380
0"
#385
0A
b101 =
b101 L
b11 @
b1000 B
b100111 #
1"
#390
0"
#395
b101000 #
b10000 B
1"
#400
0"
#405
b100000 B
b101001 #
1"
#410
0"
#415
b101010 #
b1000000 B
1"
#420
0"
#425
b10000000000000000000000000011000 ?
b1 B
b101011 #
1"
#430
0"
#435
b101100 #
b10000000000000000000000000011000 D
b11000 >
b11000 S
b10 B
1"
#440
0"
#445
b11111111111111111010011001110110 ,
b11100111011011111010000000000000 *
b11111111111111111111111001110000 .
b11111111111111111111111001110001 +
b11111111111111111111111001110110 -
b10110 &
b11111 '
b1110011 0
b10 1
b1100110 )
b11100111011011111010100011100110 /
b11100111011011111010100011100110 U
b100 B
b101101 #
1"
#450
0"
#455
b101110 #
b10 =
b10 L
b10001 @
b1000 B
1"
#460
0"
#465
b10000 B
b101111 #
1"
#470
0"
#475
b110000 #
b100000 B
1"
#480
0"
#485
b1000000 B
b110001 #
1"
#490
0"
#495
b110010 #
b10000000000000000000000000011100 ?
b1 B
1"
#500
0"
#505
b10000000000000000000000000011100 D
b11100 >
b11100 S
b10 B
b110011 #
1"
#510
0"
#515
b11111111111101011001001001001100 ,
b10100100110001011001000000000000 *
b11111111111111111111001001010100 .
b11111111111111111111101001010100 +
b11111111111111111111101001001100 -
b1100 &
b1011 '
b1010010 0
b1 1
b1 )
b110100 #
b100 B
b10100100110001011001101000000001 /
b10100100110001011001101000000001 U
1"
#520
0"
#525
b1 =
b1 L
b10100 @
b1000 B
b110101 #
1"
#530
0"
#535
b110110 #
b10000 B
03
1"
#540
0"
#545
b100000 B
b110111 #
1"
#550
0"
#555
b111000 #
b1000000 B
1"
#560
0"
#565
b10000000000000000000000000100000 ?
b1 B
b111001 #
1"
#570
0"
#575
b111010 #
b10000000000000000000000000100000 D
b100000 >
b100000 S
b10 B
1"
#580
0"
#585
b11111111111111011000010100011000 ,
b11010001100011011000000000000000 *
b11111111111111111111110100001010 .
b11111111111111111111110100001011 +
b11111111111111111111110100011000 -
b11000 &
b11011 '
b1101000 0
b0 1
b1101010 )
b11010001100011011000010111101010 /
b11010001100011011000010111101010 U
b100 B
b111011 #
1"
#590
0"
#595
b111100 #
b0 =
b0 L
b1011 @
b1000 B
1"
#600
0"
#605
13
b10000 B
b111101 #
1"
#610
0"
#615
b111110 #
b100000 B
1"
#620
0"
#625
b1000000 B
b111111 #
1"
#630
0"
#635
b1000000 #
b10000000000000000000000000100100 ?
b1 B
1"
#640
0"
#645
b10000000000000000000000000100100 D
b100100 >
b100100 S
b10 B
b1000001 #
1"
#650
0"
#655
b100111100110100100 ,
b11010010100100111000000000000 *
b110100110 .
b110100110 +
b110100101 -
b101 &
b100 '
b1101 0
b111 1
b1110000 )
b1000010 #
b100 B
b11010010100100111001101110000 /
b11010010100100111001101110000 U
1"
#660
0"
#665
b111 =
b111 L
b110 @
b1001101011001010000000000000000 F
b1001101011001010000000000000000 N
b1000 B
b1000011 #
1"
#670
0"
#675
b1000100 #
b10000 B
03
1"
#680
0"
#685
b100000 B
b1000101 #
1"
#690
0"
#695
b1000110 #
b1000000 B
1"
#700
0"
#705
b10000000000000000000000000101000 ?
b1 B
b1000111 #
1"
#710
0"
#715
b1001000 #
b10000000000000000000000000101000 D
b101000 >
b101000 S
b10 B
1"
#720
0"
#725
b11111111111100011110010010000000 ,
b11001000000000011110000000000000 *
b11111111111111111111010010000010 .
b11111111111111111111110010000010 +
b11111111111111111111110010000000 -
b0 &
b11 '
b1100100 0
b110 1
b1011100 )
b11001000000000011110000101011100 /
b11001000000000011110000101011100 U
b100 B
b1001001 #
1"
#730
0"
#735
b1001010 #
b110 =
b110 L
b10 @
b0 F
b0 N
b1000 B
1"
#740
0"
#745
b10000 B
b1001011 #
1"
#750
0"
#755
b1001100 #
b100000 B
1"
#760
0"
#765
b1000000 B
b1001101 #
1"
#770
0"
#775
b1001110 #
b10000000000000000000000000101100 ?
b1 B
1"
#780
0"
#785
b10000000000000000000000000101100 D
b101100 >
b101100 S
b10 B
b1001111 #
1"
#790
0"
#795
b11111111111101011001010101000110 ,
b11010100011001011001000000000000 *
b11111111111111111111110101011110 .
b11111111111111111111110101011111 +
b11111111111111111111110101000110 -
b110 &
b1011 '
b1101010 0
b1 1
b100111 )
b1010000 #
b100 B
b11010100011001011001111110100111 /
b11010100011001011001111110100111 U
1"
#800
0"
#805
b1 =
b1 L
b11111 @
b1000 B
b1010001 #
1"
#810
0"
#815
b1010010 #
b10000 B
1"
#820
0"
#825
b100000 B
b1010011 #
1"
#830
0"
#835
b1010100 #
b1000000 B
1"
#840
0"
#845
b10000000000000000000000000110000 ?
b1 B
b1010101 #
1"
#850
0"
#855
b1010110 #
b10000000000000000000000000110000 D
b110000 >
b110000 S
b10 B
1"
#860
0"
#865
b11111111111100011111000011000010 ,
b10001100001000011111000000000000 *
b11111111111111111111000011010110 .
b11111111111111111111100011010110 +
b11111111111111111111100011000010 -
b10 &
b11 '
b1000110 0
b111 1
b110110 )
b10001100001000011111101100110110 /
b10001100001000011111101100110110 U
b100 B
b1010111 #
1"
#870
0"
#875
b1011000 #
b111 =
b111 L
b10110 @
b1000 B
1"
#880
0"
#885
13
b10000 B
b1011001 #
1"
#890
0"
#895
b1011010 #
b100000 B
1"
#900
0"
#905
b1000000 B
b1011011 #
1"
#910
0"
#915
b1011100 #
b10000000000000000000000000110100 ?
b1 B
1"
#920
0"
#925
b10000000000000000000000000110100 D
b110100 >
b110100 S
b10 B
b1011101 #
1"
#930
0"
#935
b11111111111100000011010101000100 ,
b11010100010000000011000000000000 *
b11111111111111111111110101000010 .
b11111111111111111111110101000011 +
b11111111111111111111110101000100 -
b100 &
b0 '
b1101010 0
b11 1
b1000 )
b1011110 #
b100 B
b11010100010000000011000110001000 /
b11010100010000000011000110001000 U
1"
#940
0"
#945
b11 =
b11 L
b11 @
b1000 B
b1011111 #
1"
#950
0"
#955
b1100000 #
b10000 B
1"
#960
0"
#965
b100000 B
b1100001 #
1"
#970
0"
#975
b1100010 #
b1000000 B
1"
#980
0"
#985
b10000000000000000000000000111000 ?
b1 B
b1100011 #
1"
#990
0"
#995
b1100100 #
b10000000000000000000000000111000 D
b111000 >
b111000 S
b10 B
1"
#1000
0"
#1005
b11111111111101001011100011110000 ,
b10001111000101001011000000000000 *
b11111111111111111111000011111010 .
b11111111111111111111100011111010 +
b11111111111111111111100011110001 -
b10001 &
b1001 '
b1000111 0
b1111 )
b10001111000101001011110100001111 /
b10001111000101001011110100001111 U
b100 B
b1100101 #
1"
#1010
0"
#1015
b1100110 #
b11010 @
b1000 B
1"
#1020
0"
#1025
b10000 B
b1100111 #
1"
#1030
0"
#1035
b1101000 #
b100000 B
1"
#1040
0"
#1045
b1000000 B
b1101001 #
1"
#1050
0"
#1055
b1101010 #
b10000000000000000000000000111100 ?
b1 B
1"
#1060
0"
#1065
b10000000000000000000000000111100 D
b111100 >
b111100 S
b10 B
b1101011 #
1"
#1070
0"
#1075
b11111010111100110100 ,
b1110011010111111010000000000000 *
b111100110110 .
b11100110111 +
b11100110101 -
b10101 &
b11111 '
b111001 0
b10 1
b11 )
b1101100 #
b100 B
b1110011010111111010101110000011 /
b1110011010111111010101110000011 U
1"
#1080
0"
#1085
19
1A
b11100110101 6
b11100110101 J
b10 =
b10 L
b10111 @
b1000 B
b1101101 #
1"
#1090
0"
#1095
b1101110 #
19
1A
b10000 B
b11100110101 (
b11100110101 K
1"
#1100
0"
#1105
19
1A
b100000 B
b1101111 #
1"
#1110
0"
#1115
b100001011000100100010101110001 P
b1110000 #
b11100110101 8
b11100110101 O
19
1A
b1000000 B
1"
#1120
0"
#1125
b1000010110001001000101 2
b1000010110001001000101 T
b10000000000000000000000001000000 ?
19
1A
b1 B
b1110001 #
1"
#1130
0"
#1135
b1110010 #
19
1A
b10000000000000000000000001000000 D
b1000000 >
b1000000 S
b10 B
1"
#1140
0"
#1145
b11111111111101000100100101010000 ,
b10010101000101000100000000000000 *
b11111111111111111111100101011100 .
b11111111111111111111100101011101 +
b11111111111111111111100101010001 -
b10001 &
b1000 '
b1001010 0
b100 1
b110100 )
b10010101000101000100111010110100 /
b10010101000101000100111010110100 U
19
1A
b100 B
b1110011 #
1"
#1150
0"
#1155
b1110100 #
09
0A
b100 =
b100 L
b11101 @
b1000 B
1"
#1160
0"
#1165
03
b10000 B
b1110101 #
1"
#1170
0"
#1175
b1110110 #
b100000 B
1"
#1180
0"
#1185
b1000000 B
b1110111 #
1"
#1190
0"
#1195
b1111000 #
b10000000000000000000000001000100 ?
b1 B
1"
#1200
0"
#1205
b10000000000000000000000001000100 D
b1000100 >
b1000100 S
b10 B
b1111001 #
1"
#1210
0"
#1215
b11111111111100101001100000111010 ,
b10000011101100101001000000000000 *
b11111111111111111111000000101110 .
b11111111111111111111100000101110 +
b11111111111111111111100000111011 -
b11011 &
b101 '
b1000001 0
b1 1
b1101110 )
b1111010 #
b100 B
b10000011101100101001011101101110 /
b10000011101100101001011101101110 U
1"
#1220
0"
#1225
b1 =
b1 L
b1110 @
b1001101011001010000000000000000 E
b1001101011001010000000000000000 M
b1000 B
b1111011 #
1"
#1230
0"
#1235
b1111100 #
b1001101011001010000000000000000 7
b1001101011001010000000000000000 I
b10000 B
13
1"
#1240
0"
#1245
b1001101011001010000011100110101 (
b1001101011001010000011100110101 K
b100000 B
b1111101 #
1"
#1250
0"
#1255
b1111110 #
b1000000 B
1"
#1260
0"
#1265
b10000000000000000000000001001000 ?
b1 B
b1111111 #
1"
#1270
0"
#1275
b10000000 #
b10000000000000000000000001001000 D
b1001000 >
b1001000 S
b10 B
1"
#1280
0"
#1285
b11111111111111001011111100110000 ,
b11110011000111001011000000000000 *
b11111111111111111111111100110110 .
b11111111111111111111111100110111 +
b11111111111111111111111100110001 -
b10001 &
b11001 '
b1111001 0
b11 1
b1001011 )
b11110011000111001011101111001011 /
b11110011000111001011101111001011 U
b100 B
b10000001 #
1"
#1290
0"
#1295
b10000010 #
b11 =
b11 L
b10111 @
b0 E
b0 M
b1000 B
1"
#1300
0"
#1305
b0 7
b0 I
b10000 B
b10000011 #
1"
#1310
0"
#1315
b10000100 #
b100000 B
b11100110101 (
b11100110101 K
1"
#1320
0"
#1325
b1000000 B
b10000101 #
1"
#1330
0"
#1335
b10000110 #
b10000000000000000000000001001100 ?
b1 B
1"
#1340
0"
#1345
b10000000000000000000000001001100 D
b1001100 >
b1001100 S
b10 B
b10000111 #
1"
#1350
0"
#1355
b11111111111100100100010001110110 ,
b11000111011000100100000000000000 *
b11111111111111111111110001101110 .
b11111111111111111111110001101111 +
b11111111111111111111110001110110 -
b10110 &
b100 '
b1100011 0
b100 1
b1110001 )
b10001000 #
b100 B
b11000111011000100100011111110001 /
b11000111011000100100011111110001 U
1"
#1360
0"
#1365
b100 =
b100 L
b1111 @
b1000 B
b10001001 #
1"
#1370
0"
#1375
b10001010 #
b10000 B
03
1"
#1380
0"
#1385
b100000 B
b10001011 #
1"
#1390
0"
#1395
b10001100 #
b1000000 B
1"
#1400
0"
#1405
b10000000000000000000000001010000 ?
b1 B
b10001101 #
1"
#1410
0"
#1415
b10001110 #
b10000000000000000000000001010000 D
b1010000 >
b1010000 S
b10 B
1"
#1420
0"
