cpu.v
module alu (
  input clk,
  input [2:0] funct3,
  input [31:0] x,
  input [31:0] y,
  input alt,
  output reg [31:0] out
);
  always @(posedge clk) begin
    case (funct3) 
      3'b000: begin  // ADDI
        out <= alt ? (x - y) : (x + y);
      end
      3'b001: begin  // SLL
        out <= x << y[4:0];
      end
      3'b010: begin  // SLT
        out <= {31'b0, $signed(x) < $signed(y)};
      end
      3'b011: begin  // SLTU
        out <= {31'b0, x < y};
      end
      3'b100: begin  // XOR
        out <= x ^ y;
      end
      3'b101: begin  // SRL
        out <= alt ? (x >>> y[4:0]) : (x >> y[4:0]);
      end
      3'b110: begin  // OR
        out <= x | y;
      end
      3'b111: begin  // AND
        out <= x & y;
      end
    endcase
  end
endmodule

module cond (
  input clk, 
  input [2:0] funct3,
  input [31:0] x,
  input [31:0] y,
  output reg out
);
  always @(posedge clk) begin
    case (funct3) 
      3'b000: begin  // BEQ
        out <= x == y;
      end
      3'b001: begin  // BNE
        out <= x != y;
      end
      3'b100: begin  // BLT
        out <= $signed(x) < $signed(y);
      end
      3'b101: begin  // BGE
        out <= $signed(x) >= $signed(y);
      end
      3'b110: begin  // BLTU
        out <= x < y;
      end
      3'b111: begin  // BGEU
        out <= x >= y;
      end
    endcase
  end
endmodule

module ram (
  input clk,
  input [13:0] i_addr,
  output reg [31:0] i_data,
  input [13:0] d_addr,
  output reg [31:0] d_data,
  input [31:0] dw_data,
  input [1:0] dw_size);

  // 16 KB
  reg [31:0] mem [0:4095];
  wire [31:0] dt_data = mem[d_addr[13:2]];

  always @(posedge clk) begin
    // always aligned for instruction fetch
    i_data <= mem[i_addr[13:2]];
    // misaligned data, but it's filled with 0s
    // support some unaligned loads, but can't break word boundary
    d_data <=
      d_addr[1] ? (d_addr[0] ? (dt_data >> 24) : (dt_data >> 16))
                : (d_addr[0] ? (dt_data >> 8) : dt_data);
    // 2'b01 = 8-bit
    // 2'b10 = 16-bit
    // 2'b11 = 32-bit
    // again, can't break word boundary
    case (dw_size)
      2'b11: mem[d_addr[13:2]] <= dw_data;
      2'b10: mem[d_addr[13:2]] <= 
        d_addr[1] ? {dw_data[15:0], dt_data[15:0]} : 
                    {dt_data[31:16], dw_data[15:0]};
      2'b01: mem[d_addr[13:2]] <= 
        d_addr[1] ?
          (d_addr[0] ? {dw_data[7:0], dt_data[23:0]} : {dt_data[31:24], dw_data[7:0], dt_data[15:0]}) :
          (d_addr[0] ? {dt_data[31:16], dw_data[7:0], dt_data[7:0]} : {dt_data[31:8], dw_data[7:0]});
    endcase
  end
endmodule

// rvcore is a low performance RISC-V processor
module rvcore (
  input clk, resetn,
  output reg trap,
  output reg [31:0] pc
);

  //wire [13:0] i_addr = pc[13:0];
  reg [13:0] i_addr;
  wire [31:0] i_data;
  reg [13:0] d_addr;
  wire [31:0] d_data;
  reg [31:0] dw_data;
  reg [1:0] dw_size;
  ram r (
    .clk (clk),
    .i_data (i_data),
    .i_addr (i_addr),
    .d_data (d_data),
    .d_addr (d_addr),
    .dw_data (dw_data),
    .dw_size (dw_size)
  );

  reg [31:0] regs [0:31];
  reg [4:0] rd;

  reg [31:0] vs1;
  reg [31:0] vs2;
  reg [31:0] vpc;

  // Instruction decode and register fetch
  wire [6:0] opcode = i_data[6:0];
  wire [2:0] funct3 = i_data[14:12];
  wire [6:0] funct7 = i_data[31:25];
  wire [4:0] rs1 = i_data[19:15];
  wire [4:0] rs2 = i_data[24:20];
  wire [31:0] imm_i = {{20{i_data[31]}}, i_data[31:20]};
  wire [31:0] imm_s = {{20{i_data[31]}}, i_data[31:25], i_data[11:7]};
  wire [31:0] imm_b = {{19{i_data[31]}}, i_data[31], i_data[7], i_data[30:25], i_data[11:8], 1'b0};
  wire [31:0] imm_u = {i_data[31:12], 12'b0};
  wire [31:0] imm_j = {{11{i_data[31]}}, i_data[31], i_data[19:12], i_data[20], i_data[30:21], 1'b0};

  reg [31:0] alu_left;
  reg [31:0] alu_imm;
  reg [2:0] alu_func;
  reg alu_alt;

  wire [31:0] pend;
  reg [2:0] funct3_saved;
  wire cond_out;
  reg [1:0] update_pc;  // 2'b00: don't update, 2'b01: update always, 2'b10: update cond
  reg reg_writeback;

  wire pend_is_new_pc = update_pc[0] || (update_pc[1] && cond_out);
  reg do_load;
  reg do_store;

  reg [6:0] step;

  alu a (
    .clk (clk),
    .funct3 (alu_func),
    .x (alu_left),
    .y (alu_imm),
    .alt (alu_alt),
    .out (pend)
  );

  cond c (
    .clk (clk),
    .funct3 (funct3_saved),
    .x (vs1),
    .y (vs2),
    .out (cond_out)
  );

  /*parameter SZ = 4;
  parameter LOGCNT = 5;
  parameter BITS = 18;
  reg [2:0] risk_func;
  reg [4:0] risk_reg;
  reg [10+LOGCNT-1:0] risk_addr;
  reg [10+LOGCNT-2:0] risk_stride_x;
  reg [10+LOGCNT-2:0] risk_stride_y;
  wire [BITS*SZ*SZ-1:0] risk_reg_view;
  risk #(SZ, LOGCNT, BITS) ri (
    .clk (clk),
    .risk_func (risk_func),
    .risk_reg (risk_reg),
    .risk_addr (risk_addr),
    .risk_stride_x (risk_stride_x),
    .risk_stride_y (risk_stride_y),
    .reg_view (risk_reg_view)
  );*/

  integer i;
  always @(posedge clk) begin
    step <= step << 1;
    if (resetn) begin
      pc <= 32'h80000000;
      for (i=0; i<32; i=i+1) regs[i] <= 0;
      step <= 'b1;
      trap <= 1'b0;
    end

    // *** Instruction Fetch ***
    i_addr <= pc[13:0];
    // it sets i_data here from pc

    // *** Instruction decode and register fetch ***
    vs1 <= regs[rs1];
    vs2 <= regs[rs2];
    vpc <= pc;
    rd <= i_data[11:7];
    funct3_saved <= funct3;

    alu_func <= 3'b000;
    alu_left <= vs1;
    alu_alt <= 1'b0;
    update_pc <= 2'b00;
    reg_writeback <= 1'b0;
    do_load <= 1'b0;
    do_store <= 1'b0;
    case (opcode)
      7'b0110111: begin // LUI
        alu_imm <= imm_u;
        alu_left <= 32'b0;
        reg_writeback <= 1'b1;
      end
      7'b0000011: begin // LOAD
        alu_imm <= imm_i;
        reg_writeback <= 1'b1;
        do_load <= 1'b1;
      end
      7'b0100011: begin // STORE
        alu_imm <= imm_s;
        do_store <= 1'b1;
      end

      7'b0010111: begin // AUIPC
        alu_imm <= imm_u;
        alu_left <= pc;
        reg_writeback <= 1'b1;
      end
      7'b1100011: begin // BRANCH
        alu_imm <= imm_b;
        alu_left <= pc;
        update_pc <= 2'b10;
      end
      7'b1101111: begin // JAL
        alu_imm <= imm_j;
        alu_left <= pc;
        update_pc <= 2'b01;
        reg_writeback <= 1'b1;
      end
      7'b1100111: begin // JALR
        alu_imm <= imm_i;
        update_pc <= 2'b01;
        reg_writeback <= 1'b1;
      end

      7'b0010011: begin // IMM
        alu_imm <= imm_i;
        alu_func <= funct3;
        alu_alt <= (funct7 == 7'b0100000 && funct3 == 3'b101);
        reg_writeback <= 1'b1;
      end
      7'b0110011: begin // OP
        alu_imm <= regs[rs2];
        alu_func <= funct3;
        alu_alt <= (funct7 == 7'b0100000);
        reg_writeback <= 1'b1;
      end

      /*7'b1111111: begin // RISK
        risk_func <= funct3;
        risk_addr <= regs[rs1];
        risk_stride_x <= regs[rs2][31:16];
        risk_stride_y <= regs[rs2][15:0];
        risk_reg <= i_data[11:7];
        // 9 DWORDs
        case (funct7) 
          7'b0000000: alu_imm <= risk_reg_view[31:0];
          7'b0000001: alu_imm <= risk_reg_view[63:32];
          7'b0000010: alu_imm <= risk_reg_view[95:64];
          7'b0000011: alu_imm <= risk_reg_view[127:96];
          7'b0000100: alu_imm <= risk_reg_view[159:128];
          7'b0000101: alu_imm <= risk_reg_view[191:160];
          7'b0000110: alu_imm <= risk_reg_view[223:192];
          7'b0000111: alu_imm <= risk_reg_view[255:224];
          7'b0001000: alu_imm <= risk_reg_view[288:256];
        endcase
        alu_left <= 32'b0;
        reg_writeback <= 1'b1;
      end*/

      7'b1110011: begin // SYSTEM
        trap <= regs[3] > 0;
      end
    endcase

    // *** Execute (happens above in arith and cond) ***
    // it sets pend and cond_out here

    // *** Memory access ***
    // this sets d_data based on pend
    if (step[5] == 1'b1) begin
      d_addr <= pend[13:0];
      if (do_store) begin
        dw_data <= vs2;
        dw_size <= (funct3_saved[1:0] + 1);
      end
    end
    
    // *** Register Writeback ***
    if (step[6] == 1'b1) begin
      pc <= pend_is_new_pc ? pend : (vpc + 4);
      if (reg_writeback && rd != 5'b00000) begin
        if (do_load) begin
          case (funct3_saved)
            3'b000: regs[rd] <= {{24{d_data[7]}}, d_data[7:0]};
            3'b001: regs[rd] <= {{16{d_data[15]}}, d_data[15:0]};
            3'b010: regs[rd] <= d_data;
            3'b100: regs[rd] <= {24'b0, d_data[7:0]};
            3'b101: regs[rd] <= {16'b0, d_data[15:0]};
          endcase
        end else begin
          regs[rd] <= (pend_is_new_pc ? (vpc + 4) : pend);
        end
      end
      step <= 'b1;
      dw_size <= 2'b00;
    end
  end

endmodule

testbench.sv
`define hdl_path_regf c.regs
module testbench;

  reg clk;
  reg resetn;
  wire trap;
  reg [7:0] cnt;

  rvcore c (
    .clk (clk),
    .resetn (resetn),
    .trap (trap)
  );

  initial begin
    string firmware;
    clk = 0;
    cnt = 0;
    // put core to reset while initializing ram
    resetn = 0;

    $display("programming the mem");
    if ($value$plusargs("firmware=%s", firmware)) begin
        $display($sformatf("Using %s as firmware", firmware));
    end else begin
        $display($sformatf("Expecting a command line argument %s", firmware), "ERROR");
        $finish;
    end
    $readmemh(firmware, c.r.mem);

    $display("doing work", cnt);
    @(posedge clk);
    resetn = 1;
  end

  always
    #5 clk = !clk;

  always @(posedge clk) begin
    cnt <= cnt + 1;
    resetn <= 0;
  end

  always @(posedge clk) begin
    if (c.step[6] == 1'b1) begin
      $display("%b: %h %d pc:%h -- opcode:%b -- func:%h alt:%d left:%h imm:%h pend:%h d_addr:%h d_data:%h c.rs1:%h c.rs2:%h c.rd:%h",
        c.step, c.i_data, c.resetn, c.pc, c.opcode, c.alu_func, c.alu_alt, c.alu_left, c.alu_imm, c.pend, c.d_addr, c.d_data, c.rs1, c.rs2, c.rd);
  
      for (int i = 10; i < 18; i = i + 1) $display("regs[%1d]:%2d", i, c.regs[i]);
    end
  end

  always @(posedge trap) begin
    $display("TRAP", c.regs[3]);
    $finish;
  end

  initial begin
    int char_0, char_1, char_2, char_3;
    $dumpfile("waves.vcd");
    $dumpvars(0,testbench);
    #400
    $display("no more work ", cnt);
    $finish;
  end
endmodule

waves.vcd
$date
	Sun May 15 20:44:07 2022
$end
$version
	Icarus Verilog
$end
$timescale
	1s
$end
$scope module testbench $end
$var wire 1 ! trap $end
$var reg 1 " clk $end
$var reg 8 # cnt [7:0] $end
$var reg 1 $ resetn $end
$scope module c $end
$var wire 1 " clk $end
$var wire 1 % pend_is_new_pc $end
$var wire 1 $ resetn $end
$var wire 5 & rs2 [4:0] $end
$var wire 5 ' rs1 [4:0] $end
$var wire 32 ( pend [31:0] $end
$var wire 7 ) opcode [6:0] $end
$var wire 32 * imm_u [31:0] $end
$var wire 32 + imm_s [31:0] $end
$var wire 32 , imm_j [31:0] $end
$var wire 32 - imm_i [31:0] $end
$var wire 32 . imm_b [31:0] $end
$var wire 32 / i_data [31:0] $end
$var wire 7 0 funct7 [6:0] $end
$var wire 3 1 funct3 [2:0] $end
$var wire 32 2 d_data [31:0] $end
$var wire 1 3 cond_out $end
$var reg 1 4 alu_alt $end
$var reg 3 5 alu_func [2:0] $end
$var reg 32 6 alu_imm [31:0] $end
$var reg 32 7 alu_left [31:0] $end
$var reg 14 8 d_addr [13:0] $end
$var reg 1 9 do_load $end
$var reg 1 : do_store $end
$var reg 32 ; dw_data [31:0] $end
$var reg 2 < dw_size [1:0] $end
$var reg 3 = funct3_saved [2:0] $end
$var reg 14 > i_addr [13:0] $end
$var reg 32 ? pc [31:0] $end
$var reg 5 @ rd [4:0] $end
$var reg 1 A reg_writeback $end
$var reg 7 B step [6:0] $end
$var reg 1 ! trap $end
$var reg 2 C update_pc [1:0] $end
$var reg 32 D vpc [31:0] $end
$var reg 32 E vs1 [31:0] $end
$var reg 32 F vs2 [31:0] $end
$var integer 32 G i [31:0] $end
$scope module a $end
$var wire 1 4 alt $end
$var wire 1 " clk $end
$var wire 3 H funct3 [2:0] $end
$var wire 32 I x [31:0] $end
$var wire 32 J y [31:0] $end
$var reg 32 K out [31:0] $end
$upscope $end
$scope module c $end
$var wire 1 " clk $end
$var wire 3 L funct3 [2:0] $end
$var wire 32 M x [31:0] $end
$var wire 32 N y [31:0] $end
$var reg 1 3 out $end
$upscope $end
$scope module r $end
$var wire 1 " clk $end
$var wire 14 O d_addr [13:0] $end
$var wire 32 P dt_data [31:0] $end
$var wire 32 Q dw_data [31:0] $end
$var wire 2 R dw_size [1:0] $end
$var wire 14 S i_addr [13:0] $end
$var reg 32 T d_data [31:0] $end
$var reg 32 U i_data [31:0] $end
$upscope $end
$upscope $end
$scope begin $ivl_for_loop0 $end
$var integer 32 V i [31:0] $end
$upscope $end
$scope begin $unm_blk_1 $end
$upscope $end
$scope begin $unm_blk_8 $end
$upscope $end
$upscope $end
$enddefinitions $end
#0
$dumpvars
b0 V
bx U
bx T
bx S
bx R
bx Q
bx P
bx O
bx N
bx M
bx L
bx K
bx J
bx I
bx H
bx G
bx F
bx E
bx D
bx C
bx B
xA
bx @
bx ?
bx >
bx =
bx <
bx ;
x:
x9
bx 8
bx 7
bx 6
bx 5
x4
x3
bx 2
bx 1
bx 0
bx /
bx0 .
bx -
bx0 ,
bx +
bx000000000000 *
bx )
bx (
bx '
bx &
x%
0$
b0 #
0"
x!
$end
#5
0%
0:
09
0A
b0 C
04
b0 5
b0 H
0!
b10000000000000000000000000000000 ?
b1 B
b1 #
b100000 G
0$
1"
#10
0"
#15
b10 #
b10000000000000000000000000000000 D
b0 >
b0 S
b10 B
1"
#20
0"
#25
b1010000000000001010 ,
b101001010000000000000000 *
b1010 .
b1010 +
b1010 -
b1010 &
b1010 '
b0 0
b0 1
b10011 )
b101001010000010100010011 /
b101001010000010100010011 U
b100 B
b11 #
1"
#30
0"
#35
b100 #
1A
b1010 6
b1010 J
b0 =
b0 L
b1010 @
b0 F
b0 N
b0 E
b0 M
b1000 B
1"
#40
0"
#45
13
1A
b0 7
b0 I
b10000 B
b101 #
1"
#50
0"
#55
b110 #
1A
b100000 B
b1010 (
b1010 K
1"
#60
0"
#65
b101101010000011000110011 P
b1010 8
b1010 O
1A
b1000000 B
b111 #
1"
#70
0"
#75
b1000 #
b0 <
b0 R
b10000000000000000000000000000100 ?
1A
b1 B
b10110101 2
b10110101 T
b10010 V
1"
#80
0"
#85
1A
b10000000000000000000000000000100 D
b1010 F
b1010 N
b1010 E
b1010 M
b100 >
b100 S
b10 B
b1001 #
1"
#90
0"
#95
b1011000000000001010 ,
b101001011000000000000000 *
b100000001010 .
b1011 +
b1011 '
b1010 #
1A
b1010 7
b1010 I
b100 B
b101001011000010110010011 /
b101001011000010110010011 U
1"
#100
0"
#105
b10100 (
b10100 K
1A
b1011 @
b0 E
b0 M
b1000 B
b1011 #
1"
#110
0"
#115
b1100 #
1A
b0 7
b0 I
b10000 B
03
1"
#120
0"
#125
b1010 (
b1010 K
1A
b100000 B
b1101 #
1"
#130
0"
#135
b1110 #
1A
b1000000 B
1"
#140
0"
#145
b10000000000000000000000000001000 ?
1A
b1 B
b1111 #
b10010 V
1"
#150
0"
#155
b10000 #
1A
b10000000000000000000000000001000 D
b1010 E
b1010 M
b1000 >
b1000 S
b10 B
1"
#160
0"
#165
b1010000100000001010 ,
b101101010000000000000000 *
b1100 .
b1100 +
b1011 -
b1011 &
b1010 '
b110011 )
b101101010000011000110011 /
b101101010000011000110011 U
13
1A
b1010 7
b1010 I
b100 B
b10001 #
1"
#170
0"
#175
b10010 #
1A
b1100 @
b1000 B
b10100 (
b10100 K
1"
#180
0"
#185
1A
b10000 B
b10011 #
1"
#190
0"
#195
b10100 #
1A
b100000 B
1"
#200
0"
#205
bx P
b10100 8
b10100 O
1A
b1000000 B
b10101 #
1"
#210
0"
#215
b10110 #
b10000000000000000000000000001100 ?
1A
b1 B
bx 2
bx T
b10010 V
1"
#220
0"
#225
1A
b10000000000000000000000000001100 D
b1100 >
b1100 S
b10 B
b10111 #
1"
#230
0"
#235
b1100000110000001010 ,
b1000000101101100000000000000000 *
b110000001100 .
b10000001101 +
b10000001011 -
b1100 '
b100000 0
b11000 #
1A
b100 B
b1000000101101100000011010110011 /
b1000000101101100000011010110011 U
1"
#240
0"
#245
14
1A
b1101 @
b10100 E
b10100 M
b1000 B
b11001 #
1"
#250
0"
#255
b11010 #
1A
14
b10100 7
b10100 I
b10000 B
03
b0 (
b0 K
1"
#260
0"
#265
b1010 (
b1010 K
1A
14
b100000 B
b11011 #
1"
#270
0"
#275
b101101010000011000110011 P
b11100 #
b1010 8
b1010 O
1A
14
b1000000 B
1"
#280
0"
#285
b10110101 2
b10110101 T
b10000000000000000000000000010000 ?
1A
14
b1 B
b11101 #
b10010 V
1"
#290
0"
#295
b11110 #
1A
14
b10000000000000000000000000010000 D
b10000 >
b10000 S
b10 B
1"
#300
0"
#305
bx0 ,
bx000000000000 *
bx0 .
bx +
bx -
bx &
bx '
bx 0
bx 1
bx )
bx /
bx U
1A
14
b100 B
b11111 #
1"
#310
0"
#315
b100000 #
0A
04
bx =
bx L
bx @
bx F
bx N
bx E
bx M
b1000 B
1"
#320
0"
#325
b11110 (
b11110 K
bx 7
bx I
b10000 B
b100001 #
1"
#330
0"
#335
b100010 #
b100000 B
bx (
bx K
1"
#340
0"
#345
bx P
bx 8
bx O
b1000000 B
b100011 #
1"
#350
0"
#355
b100100 #
b10000000000000000000000000010100 ?
b1 B
bx 2
bx T
b10010 V
1"
#360
0"
#365
b10000000000000000000000000010100 D
b10100 >
b10100 S
b10 B
b100101 #
1"
#370
0"
#375
b100110 #
b100 B
1"
#380
0"
#385
b1000 B
b100111 #
1"
#390
0"
#395
b101000 #
b10000 B
1"
