Final.v

module risk_single_mem #(parameter LINE=18) (
  input clk,
  input [9:0] addr,
  output reg [LINE-1:0] data_r,
  input [LINE-1:0] data_w,
  input we
);
  reg [LINE-1:0] mem [0:1023];
  always @(posedge clk) begin
    if (we) begin
      mem[addr] <= data_w;
    end else begin
      data_r <= mem[addr];
    end
  end
endmodule


// this is hard to synthesize
module risk_mem #(parameter SZ=4, LOGCNT=5, BITS=18) (
  input clk,
  input [10+LOGCNT-1:0] addr,
  input [10+LOGCNT-2:0] stride_x,
  input [10+LOGCNT-2:0] stride_y,
  input [BITS*SZ*SZ-1:0] dat_w,
  input we,
  output reg [BITS*SZ*SZ-1:0] dat_r
);
  parameter CNT=(1<<LOGCNT);


  parameter SZ_X=1;
  parameter LINE=BITS*SZ;

  // 1 cycle to get all the addresses
  reg [(10+LOGCNT)*SZ*SZ_X-1:0] addrs;

  generate
    genvar x,y;
    for (y=0; y<SZ; y=y+1) begin
      for (x=0; x<SZ_X; x=x+1) begin
        always @(posedge clk) begin
          addrs[(y*SZ_X+x)*(10+LOGCNT) +: (10+LOGCNT)] <= addr + stride_x*x + stride_y*y;
        end
      end
    end
  endgenerate
  
  reg [CNT*SZ_X*SZ-1:0] mask;
  wire [LINE*CNT-1:0] outs;

  generate
    genvar i,k;

    // CNT number of priority encoders of SZ*SZ
    for (i=0; i<CNT; i=i+1) begin
      reg [9:0] taddr;
      reg [LINE-1:0] in;
      wire [LINE-1:0] out;
      risk_single_mem #(LINE) rsm(
        .clk(clk),
        .addr(taddr),
        .data_r(out),
        .data_w(in),
        .we(we)
      );

      integer l;
      always @(posedge clk) begin
        //ens[i] <= 'b0;
        mask[i*SZ_X*SZ +: SZ_X*SZ] <= 'b0;
        for (l=SZ_X*SZ-1; l>=0; l=l-1) begin
          if (addrs[(10+LOGCNT)*l +: LOGCNT] == i) begin
            mask[i*SZ_X*SZ +: SZ_X*SZ] <= (1 << l);
            taddr <= addrs[(10+LOGCNT)*l+LOGCNT +: 10];
            in <= dat_w[LINE*l +: LINE];
          end
        end
      end
      assign outs[i*LINE +: LINE] = out;
    end

    // this is SZ*SZ number of CNT to 1 muxes. these don't have to be priority encoders, really just a big or gate
    for (k=0; k<SZ_X*SZ; k=k+1) begin
      wire [CNT-1:0] lmask;
      for (i=0; i < CNT; i=i+1) assign lmask[i] = mask[i*SZ_X*SZ + k];

      integer l;
      always @(posedge clk) begin
        if (lmask != 'b0) begin
          dat_r[LINE*k +: LINE] = 'b0;
          for (l=0; l<CNT; l=l+1)
            dat_r[LINE*k +: LINE] = dat_r[LINE*k +: LINE] | (outs[LINE*l +: LINE] & {LINE{lmask[l]}});
        end
      end
    end

  endgenerate

endmodule


module risk_alu (
  input clk
);

endmodule

module alu (
  input clk,
  input [2:0] funct3,
  input [31:0] x,
  input [31:0] y,
  output reg [31:0] out
);
  always @(posedge clk) begin
    case (funct3) 
      3'b000: begin  // ADD
        out <= x + y;
      end

      3'b001: begin  // SUB
        out <= x - y;
      end

      3'b010: begin  // NOT
        out <= !x;
      end

      3'b011: begin  // SL
        out <= x << y;
      end

      3'b100: begin  // SR
        out <= x >> y;
      end

      3'b101: begin  // XOR
        out <= x ^ y;
      end

      3'b110: begin  // OR
        out <= x | y;
      end

      3'b111: begin  // AND
        out <= x & y;
      end
      default: begin
        out <= 0;
      end
    endcase
  end
endmodule

module cond (
  input clk, 
  input [2:0] funct3,
  input [31:0] x,
  input [31:0] y,
  output reg out
);
  always @(posedge clk) begin
    case (funct3) 
      3'b000: begin  // BEQ
        out <= x == y;
      end
      3'b001: begin  // BNE
        out <= x != y;
      end
      3'b100: begin  // BLT
        out <= $signed(x) < $signed(y);
      end
      3'b101: begin  // BGE
        out <= $signed(x) >= $signed(y);
      end
      3'b110: begin  // BLTU
        out <= x < y;
      end
      3'b111: begin  // BGEU
        out <= x >= y;
      end
    endcase
  end
endmodule

module ram (
  input clk,
  input [13:0] i_addr,
  output reg [31:0] i_data,
  input [13:0] d_addr,
  output reg [31:0] d_data,
  input [31:0] dw_data,
  input [1:0] dw_size);

  // 16 KB
  reg [31:0] mem [0:4095];
  wire [31:0] dt_data = mem[d_addr[13:2]];

  always @(posedge clk) begin
    // always aligned for instruction fetch
    i_data <= mem[i_addr[13:2]];
    // misaligned data, but it's filled with 0s
    // support some unaligned loads, but can't break word boundary
    d_data <=
      d_addr[1] ? (d_addr[0] ? (dt_data >> 24) : (dt_data >> 16))
                : (d_addr[0] ? (dt_data >> 8) : dt_data);
    // 2'b01 = 8-bit
    // 2'b10 = 16-bit
    // 2'b11 = 32-bit
    // again, can't break word boundary
    case (dw_size)
      2'b11: mem[d_addr[13:2]] <= dw_data;
      2'b10: mem[d_addr[13:2]] <= 
        d_addr[1] ? {dw_data[15:0], dt_data[15:0]} : 
                    {dt_data[31:16], dw_data[15:0]};
      2'b01: mem[d_addr[13:2]] <= 
        d_addr[1] ?
          (d_addr[0] ? {dw_data[7:0], dt_data[23:0]} : {dt_data[31:24], dw_data[7:0], dt_data[15:0]}) :
          (d_addr[0] ? {dt_data[31:16], dw_data[7:0], dt_data[7:0]} : {dt_data[31:8], dw_data[7:0]});
    endcase
  end
endmodule

// twitchcore is a low performance RISC-V processor
module twitchcore (
  input clk, resetn,
  output reg trap,
  output reg [31:0] pc
);

  //wire [13:0] i_addr = pc[13:0];
  reg [13:0] i_addr;
  wire [31:0] i_data;
  reg [13:0] d_addr;
  wire [31:0] d_data;
  reg [31:0] dw_data;
  reg [1:0] dw_size;
  ram r (
    .clk (clk),
    .i_data (i_data),
    .i_addr (i_addr),
    .d_data (d_data),
    .d_addr (d_addr),
    .dw_data (dw_data),
    .dw_size (dw_size)
  );

  reg [31:0] regs [0:31];
  reg [4:0] rd;

  reg [31:0] vs1;
  reg [31:0] vs2;
  reg [31:0] vpc;

  // Instruction decode and register fetch
  wire [6:0] opcode = i_data[6:0];
  wire [2:0] funct3 = i_data[14:12];
  wire [6:0] funct7 = i_data[31:25];
  wire [4:0] rs1 = i_data[19:15];
  wire [4:0] rs2 = i_data[24:20];
  wire [31:0] imm_i = {{20{i_data[31]}}, i_data[31:20]};
  wire [31:0] imm_s = {{20{i_data[31]}}, i_data[31:25], i_data[11:7]};
  wire [31:0] imm_b = {{19{i_data[31]}}, i_data[31], i_data[7], i_data[30:25], i_data[11:8], 1'b0};
  wire [31:0] imm_u = {i_data[31:12], 12'b0};
  wire [31:0] imm_j = {{11{i_data[31]}}, i_data[31], i_data[19:12], i_data[20], i_data[30:21], 1'b0};

  reg [31:0] alu_left;
  reg [31:0] alu_imm;
  reg [2:0] alu_func;

  wire [31:0] pend;
  reg [2:0] funct3_saved;
  wire cond_out;
  reg [1:0] update_pc;  // 2'b00: don't update, 2'b01: update always, 2'b10: update cond
  reg reg_writeback;

  wire pend_is_new_pc = update_pc[0] || (update_pc[1] && cond_out);
  reg do_load;
  reg do_store;

  reg [6:0] step;

  alu a (
    .clk (clk),
    .funct3 (alu_func),
    .x (alu_left),
    .y (alu_imm),
    .out (pend)
  );

  cond c (
    .clk (clk),
    .funct3 (funct3_saved),
    .x (vs1),
    .y (vs2),
    .out (cond_out)
  );



  integer i;
  always @(posedge clk) begin
    step <= step << 1;
    if (resetn) begin
      pc <= 32'h80000000;
      for (i=0; i<32; i=i+1) regs[i] <= 0;
      step <= 'b1;
      trap <= 1'b0;
    end

    // *** Instruction Fetch ***
    i_addr <= pc[13:0];
    // it sets i_data here from pc

    // *** Instruction decode and register fetch ***
    vs1 <= regs[rs1];
    vs2 <= regs[rs2];
    vpc <= pc;
    rd <= i_data[11:7];
    funct3_saved <= funct3;

    alu_func <= 3'b000;
    alu_left <= vs1;
    update_pc <= 2'b00;
    reg_writeback <= 1'b0;
    do_load <= 1'b0;
    do_store <= 1'b0;
    case (opcode)
      7'b0110111: begin // LUI
        alu_imm <= imm_u;
        alu_left <= 32'b0;
        reg_writeback <= 1'b1;
      end
      7'b0000011: begin // LOAD
        alu_imm <= imm_i;
        reg_writeback <= 1'b1;
        do_load <= 1'b1;
      end
      7'b0100011: begin // STORE
        alu_imm <= imm_s;
        do_store <= 1'b1;
      end

      7'b0010111: begin // AUIPC
        alu_imm <= imm_u;
        alu_left <= pc;
        reg_writeback <= 1'b1;
      end
      7'b1100011: begin // BRANCH
        alu_imm <= imm_b;
        alu_left <= pc;
        update_pc <= 2'b10;
      end
      7'b1101111: begin // JAL
        alu_imm <= imm_j;
        alu_left <= pc;
        update_pc <= 2'b01;
        reg_writeback <= 1'b1;
      end
      7'b1100111: begin // JALR
        alu_imm <= imm_i;
        update_pc <= 2'b01;
        reg_writeback <= 1'b1;
      end

      7'b0010011: begin // IMM
        alu_imm <= imm_i;
        alu_func <= funct3;
        reg_writeback <= 1'b1;
      end
      7'b0110011: begin // OP
        alu_imm <= regs[rs2];
        alu_func <= funct3;
        reg_writeback <= 1'b1;
      end

      7'b1110011: begin // SYSTEM
        trap <= regs[3] > 0;
      end
    endcase

    // *** Execute (happens above in arith and cond) ***
    // it sets pend and cond_out here

    // *** Memory access ***
    // this sets d_data based on pend
    if (step[5] == 1'b1) begin
      d_addr <= pend[13:0];
      if (do_store) begin
        dw_data <= vs2;
        dw_size <= (funct3_saved[1:0] + 1);
      end
    end
    
    // *** Register Writeback ***
    if (step[6] == 1'b1) begin
      pc <= pend_is_new_pc ? pend : (vpc + 4);
      if (reg_writeback && rd != 5'b00000) begin
        if (do_load) begin
          case (funct3_saved)
            3'b000: regs[rd] <= {{24{d_data[7]}}, d_data[7:0]};
            3'b001: regs[rd] <= {{16{d_data[15]}}, d_data[15:0]};
            3'b010: regs[rd] <= d_data;
            3'b100: regs[rd] <= {24'b0, d_data[7:0]};
            3'b101: regs[rd] <= {16'b0, d_data[15:0]};
          endcase
        end else begin
          regs[rd] <= (pend_is_new_pc ? (vpc + 4) : pend);
        end
      end
      step <= 'b1;
      dw_size <= 2'b00;
    end
  end

endmodule

testbench.sv
`define hdl_path_regf c.regs
module testbench;

  reg clk;
  reg resetn;
  wire trap;
  reg [7:0] cnt;

  twitchcore c (
    .clk (clk),
    .resetn (resetn),
    .trap (trap)
  );

  initial begin
    string firmware;
    clk = 0;
    cnt = 0;
    // put core to reset while initializing ram
    resetn = 0;

    $display("programming the mem");
    if ($value$plusargs("firmware=%s", firmware)) begin
        $display($sformatf("Using %s as firmware", firmware));
    end else begin
        $display($sformatf("Expecting a command line argument %s", firmware), "ERROR");
        $finish;
    end
    $readmemh(firmware, c.r.mem);

    $display("doing work", cnt);
    @(posedge clk);
    resetn = 1;
  end

  always
    #5 clk = !clk;

  always @(posedge clk) begin
    cnt <= cnt + 1;
    resetn <= 0;
  end



  always @(posedge clk) begin
    if (c.step[6] == 1'b1) begin
      $display("%b: %h %d pc:%h -- opcode:%b -- func:%h left:%h imm:%h pend:%h d_addr:%h d_data:%h trap:%d rs1:%h rs2:%h",
        c.step, c.i_data, c.resetn, c.pc, c.opcode, c.alu_func, c.alu_left, c.alu_imm, c.pend, c.d_addr, c.d_data, c.trap, c.rs1, c.rs2);
    end
  end

  always @(posedge trap) begin
    $display("TRAP", c.regs[3]);
    $finish;
  end

  initial begin
    int char_0, char_1, char_2, char_3;
    $dumpfile("waves.vcd");
    $dumpvars(0,testbench);
    #50000
    $display("no more work ", cnt);
    // At the end of risc-v test, we should see OK\n or
    // Err\n in registers a0-a3 ()
    char_0 = `hdl_path_regf[10];
    char_1 = `hdl_path_regf[11];
    char_2 = `hdl_path_regf[12];
    char_3 = `hdl_path_regf[13];
    $display($sformatf("RISC-V TEST Result: %s%s%s%s", char_0, char_1, char_2, char_3));
    $finish;
  end
endmodule

waves.vcd
$date
	Sun May 15 11:05:03 2022
$end
$version
	Icarus Verilog
$end
$timescale
	1s
$end
$scope module testbench $end
$var wire 1 ! trap $end
$var reg 1 " clk $end
$var reg 8 # cnt [7:0] $end
$var reg 1 $ resetn $end
$scope module c $end
$var wire 1 " clk $end
$var wire 1 % pend_is_new_pc $end
$var wire 1 $ resetn $end
$var wire 5 & rs2 [4:0] $end
$var wire 5 ' rs1 [4:0] $end
$var wire 32 ( pend [31:0] $end
$var wire 7 ) opcode [6:0] $end
$var wire 32 * imm_u [31:0] $end
$var wire 32 + imm_s [31:0] $end
$var wire 32 , imm_j [31:0] $end
$var wire 32 - imm_i [31:0] $end
$var wire 32 . imm_b [31:0] $end
$var wire 32 / i_data [31:0] $end
$var wire 7 0 funct7 [6:0] $end
$var wire 3 1 funct3 [2:0] $end
$var wire 32 2 d_data [31:0] $end
$var wire 1 3 cond_out $end
$var reg 3 4 alu_func [2:0] $end
$var reg 32 5 alu_imm [31:0] $end
$var reg 32 6 alu_left [31:0] $end
$var reg 14 7 d_addr [13:0] $end
$var reg 1 8 do_load $end
$var reg 1 9 do_store $end
$var reg 32 : dw_data [31:0] $end
$var reg 2 ; dw_size [1:0] $end
$var reg 3 < funct3_saved [2:0] $end
$var reg 14 = i_addr [13:0] $end
$var reg 32 > pc [31:0] $end
$var reg 5 ? rd [4:0] $end
$var reg 1 @ reg_writeback $end
$var reg 7 A step [6:0] $end
$var reg 1 ! trap $end
$var reg 2 B update_pc [1:0] $end
$var reg 32 C vpc [31:0] $end
$var reg 32 D vs1 [31:0] $end
$var reg 32 E vs2 [31:0] $end
$var integer 32 F i [31:0] $end
$scope module a $end
$var wire 1 " clk $end
$var wire 3 G funct3 [2:0] $end
$var wire 32 H x [31:0] $end
$var wire 32 I y [31:0] $end
$var reg 32 J out [31:0] $end
$upscope $end
$scope module c $end
$var wire 1 " clk $end
$var wire 3 K funct3 [2:0] $end
$var wire 32 L x [31:0] $end
$var wire 32 M y [31:0] $end
$var reg 1 3 out $end
$upscope $end
$scope module r $end
$var wire 1 " clk $end
$var wire 14 N d_addr [13:0] $end
$var wire 32 O dt_data [31:0] $end
$var wire 32 P dw_data [31:0] $end
$var wire 2 Q dw_size [1:0] $end
$var wire 14 R i_addr [13:0] $end
$var reg 32 S d_data [31:0] $end
$var reg 32 T i_data [31:0] $end
$upscope $end
$upscope $end
$scope begin $unm_blk_1 $end
$upscope $end
$scope begin $unm_blk_8 $end
$var integer 32 U char_0 [31:0] $end
$var integer 32 V char_1 [31:0] $end
$var integer 32 W char_2 [31:0] $end
$var integer 32 X char_3 [31:0] $end
$upscope $end
$upscope $end
$enddefinitions $end
#0
$dumpvars
b0 X
b0 W
b0 V
b0 U
bx T
bx S
bx R
bx Q
bx P
bx O
bx N
bx M
bx L
bx K
bx J
bx I
bx H
bx G
bx F
bx E
bx D
bx C
bx B
bx A
x@
bx ?
bx >
bx =
bx <
bx ;
bx :
x9
x8
bx 7
bx 6
bx 5
bx 4
x3
bx 2
bx 1
bx 0
bx /
bx0 .
bx -
bx0 ,
bx +
bx000000000000 *
bx )
bx (
bx '
bx &
x%
0$
b0 #
0"
x!
$end
#5
0%
b0 (
b0 J
09
08
0@
b0 B
b0 4
b0 G
0!
b10000000000000000000000000000000 >
b1 A
b1 #
b100000 F
0$
1"
#10
0"
#15
b10 #
b10000000000000000000000000000000 C
b0 =
b0 R
b10 A
bx (
bx J
1"
#20
0"
#25
b11111111111101000000110110100000 ,
b11011010000101000000000000000000 *
b11111111111111111111110110111110 .
b11111111111111111111110110111111 +
b11111111111111111111110110100001 -
b1 &
b1000 '
b1101101 0
b0 1
b101011 )
b11011010000101000000111110101011 /
b11011010000101000000111110101011 T
b100 A
b11 #
1"
#30
0"
#35
b100 #
b0 <
b0 K
b11111 ?
b0 E
b0 M
b0 D
b0 L
b1000 A
1"
#40
0"
#45
13
b0 6
b0 H
b10000 A
b101 #
1"
#50
0"
#55
b110 #
b100000 A
1"
#60
0"
#65
b1000000 A
b111 #
1"
#70
0"
#75
b1000 #
b0 ;
b0 Q
b10000000000000000000000000000100 >
b1 A
1"
#80
0"
#85
b10000000000000000000000000000100 C
b100 =
b100 R
b10 A
b1001 #
1"
#90
0"
#95
b11111111111110000001111000001010 ,
b11100000101110000001000000000000 *
b11111111111111111111111000000110 .
b11111111111111111111111000000111 +
b11111111111111111111111000001011 -
b1011 &
b10000 '
b1110000 0
b1 1
b1010010 )
b1010 #
b100 A
b11100000101110000001001111010010 /
b11100000101110000001001111010010 T
1"
#100
0"
#105
b1 <
b1 K
b111 ?
b1000 A
b1011 #
1"
#110
0"
#115
b1100 #
b10000 A
03
1"
#120
0"
#125
b100000 A
b1101 #
1"
#130
0"
#135
b1110 #
b1000000 A
1"
#140
0"
#145
b10000000000000000000000000001000 >
b1 A
b1111 #
1"
#150
0"
#155
b10000 #
b10000000000000000000000000001000 C
b1000 =
b1000 R
b10 A
1"
#160
0"
#165
b11111111111101101001111111101000 ,
b11111110100101101001000000000000 *
b11111111111111111111111111111110 .
b11111111111111111111111111111111 +
b11111111111111111111111111101001 -
b1001 &
b1101 '
b1111111 0
b100100 )
b11111110100101101001111110100100 /
b11111110100101101001111110100100 T
b100 A
b10001 #
1"
#170
0"
#175
b10010 #
b11111 ?
b1000 A
1"
#180
0"
#185
b10000 A
b10011 #
1"
#190
0"
#195
b10100 #
b100000 A
1"
#200
0"
#205
b1000000 A
b10101 #
1"
#210
0"
#215
b10110 #
b10000000000000000000000000001100 >
b1 A
1"
#220
0"
#225
b10000000000000000000000000001100 C
b1100 =
b1100 R
b10 A
b10111 #
1"
#230
0"
#235
b11101111110011001000 ,
b1001100100111101111000000000000 *
b10011001110 .
b10011001110 +
b10011001001 -
b11101 '
b100110 0
b111 1
b110110 )
b11000 #
b100 A
b1001100100111101111011100110110 /
b1001100100111101111011100110110 T
1"
#240
0"
#245
b111 <
b111 K
b1110 ?
b1000 A
b11001 #
1"
#250
0"
#255
b11010 #
b10000 A
13
1"
#260
0"
#265
b100000 A
b11011 #
1"
#270
0"
#275
b11100 #
b1000000 A
1"
#280
0"
#285
b10000000000000000000000000010000 >
b1 A
b11101 #
1"
#290
0"
#295
b11110 #
b10000000000000000000000000010000 C
b10000 =
b10000 R
b10 A
1"
#300
0"
#305
b1010000010011010110 ,
b1001101011001010000000000000000 *
b110011000100 .
b10011000101 +
b10011010110 -
b10110 &
b1010 '
b0 1
b110111 )
b1001101011001010000001010110111 /
b1001101011001010000001010110111 T
b100 A
b11111 #
1"
#310
0"
#315
b100000 #
1@
b1001101011001010000000000000000 5
b1001101011001010000000000000000 I
b0 <
b0 K
b101 ?
b1000 A
1"
#320
0"
#325
b1001101011001010000000000000000 (
b1001101011001010000000000000000 J
1@
b10000 A
b100001 #
1"
#330
0"
#335
b100010 #
1@
b100000 A
1"
#340
0"
#345
b11011010000101000000111110101011 O
b0 7
b0 N
1@
b1000000 A
b100011 #
1"
#350
0"
#355
b100100 #
b10000000000000000000000000010100 >
1@
b1 A
b11011010000101000000111110101011 2
b11011010000101000000111110101011 S
1"
#360
0"
#365
1@
b10000000000000000000000000010100 C
b10100 =
b10100 R
b10 A
b100101 #
1"
#370
0"
#375
b11111111111100001101000011000110 ,
b10001100011000001101000000000000 *
b11111111111111111111100011000010 .
b11111111111111111111100011000011 +
b11111111111111111111100011000110 -
b110 &
b1 '
b1000110 0
b101 1
b1110000 )
b100110 #
1@
b100 A
b10001100011000001101000111110000 /
b10001100011000001101000111110000 T
1"
#380
0"
#385
0@
b101 <
b101 K
b11 ?
b1000 A
b100111 #
1"
#390
0"
#395
b101000 #
b10000 A
1"
#400
0"
#405
b100000 A
b101001 #
1"
#410
0"
#415
b101010 #
b1000000 A
1"
#420
0"
#425
b10000000000000000000000000011000 >
b1 A
b101011 #
1"
#430
0"
#435
b101100 #
b10000000000000000000000000011000 C
b11000 =
b11000 R
b10 A
1"
#440
0"
#445
b11111111111111111010011001110110 ,
b11100111011011111010000000000000 *
b11111111111111111111111001110000 .
b11111111111111111111111001110001 +
b11111111111111111111111001110110 -
b10110 &
b11111 '
b1110011 0
b10 1
b1100110 )
b11100111011011111010100011100110 /
b11100111011011111010100011100110 T
b100 A
b101101 #
1"
#450
0"
#455
b101110 #
b10 <
b10 K
b10001 ?
b1000 A
1"
#460
0"
#465
b10000 A
b101111 #
1"
#470
0"
#475
b110000 #
b100000 A
1"
#480
0"
#485
b1000000 A
b110001 #
1"
#490
0"
#495
b110010 #
b10000000000000000000000000011100 >
b1 A
1"
#500
0"
#505
b10000000000000000000000000011100 C
b11100 =
b11100 R
b10 A
b110011 #
1"
#510
0"
#515
b11111111111101011001001001001100 ,
b10100100110001011001000000000000 *
b11111111111111111111001001010100 .
b11111111111111111111101001010100 +
b11111111111111111111101001001100 -
b1100 &
b1011 '
b1010010 0
b1 1
b1 )
b110100 #
b100 A
b10100100110001011001101000000001 /
b10100100110001011001101000000001 T
1"
#520
0"
#525
b1 <
b1 K
b10100 ?
b1000 A
b110101 #
1"
#530
0"
#535
b110110 #
b10000 A
03
1"
#540
0"
#545
b100000 A
b110111 #
1"
#550
0"
#555
b111000 #
b1000000 A
1"
#560
0"
#565
b10000000000000000000000000100000 >
b1 A
b111001 #
1"
#570
0"
#575
b111010 #
b10000000000000000000000000100000 C
b100000 =
b100000 R
b10 A
1"
#580
0"
#585
b11111111111111011000010100011000 ,
b11010001100011011000000000000000 *
b11111111111111111111110100001010 .
b11111111111111111111110100001011 +
b11111111111111111111110100011000 -
b11000 &
b11011 '
b1101000 0
b0 1
b1101010 )
b11010001100011011000010111101010 /
b11010001100011011000010111101010 T
b100 A
b111011 #
1"
#590
0"
#595
b111100 #
b0 <
b0 K
b1011 ?
b1000 A
1"
#600
0"
#605
13
b10000 A
b111101 #
1"
#610
0"
#615
b111110 #
b100000 A
1"
#620
0"
#625
b1000000 A
b111111 #
1"
#630
0"
#635
b1000000 #
b10000000000000000000000000100100 >
b1 A
1"
#640
0"
#645
b10000000000000000000000000100100 C
b100100 =
b100100 R
b10 A
b1000001 #
1"
#650
0"
#655
b100111100110100100 ,
b11010010100100111000000000000 *
b110100110 .
b110100110 +
b110100101 -
b101 &
b100 '
b1101 0
b111 1
b1110000 )
b1000010 #
b100 A
b11010010100100111001101110000 /
b11010010100100111001101110000 T
1"
#660
0"
#665
b111 <
b111 K
b110 ?
b1001101011001010000000000000000 E
b1001101011001010000000000000000 M
b1000 A
b1000011 #
1"
#670
0"
#675
b1000100 #
b10000 A
03
1"
#680
0"
#685
b100000 A
b1000101 #
1"
#690
0"
#695
b1000110 #
b1000000 A
1"
#700
0"
#705
b10000000000000000000000000101000 >
b1 A
b1000111 #
1"
#710
0"
#715
b1001000 #
b10000000000000000000000000101000 C
b101000 =
b101000 R
b10 A
1"
#720
0"
#725
b11111111111100011110010010000000 ,
b11001000000000011110000000000000 *
b11111111111111111111010010000010 .
b11111111111111111111110010000010 +
b11111111111111111111110010000000 -
b0 &
b11 '
b1100100 0
b110 1
b1011100 )
b11001000000000011110000101011100 /
b11001000000000011110000101011100 T
b100 A
b1001001 #
1"
#730
0"
#735
b1001010 #
b110 <
b110 K
b10 ?
b0 E
b0 M
b1000 A
1"
#740
0"
#745
b10000 A
b1001011 #
1"
#750
0"
#755
b1001100 #
b100000 A
1"
#760
0"
#765
b1000000 A
b1001101 #
1"
#770
0"
#775
b1001110 #
b10000000000000000000000000101100 >
b1 A
1"
#780
0"
#785
b10000000000000000000000000101100 C
b101100 =
b101100 R
b10 A
b1001111 #
1"
#790
0"
#795
b11111111111101011001010101000110 ,
b11010100011001011001000000000000 *
b11111111111111111111110101011110 .
b11111111111111111111110101011111 +
b11111111111111111111110101000110 -
b110 &
b1011 '
b1101010 0
b1 1
b100111 )
b1010000 #
b100 A
b11010100011001011001111110100111 /
b11010100011001011001111110100111 T
1"
#800
0"
#805
b1 <
b1 K
b11111 ?
b1000 A
b1010001 #
1"
#810
0"
#815
b1010010 #
b10000 A
1"
#820
0"
#825
b100000 A
b1010011 #
1"
#830
0"
#835
b1010100 #
b1000000 A
1"
#840
0"
#845
b10000000000000000000000000110000 >
b1 A
b1010101 #
1"
#850
0"
#855
b1010110 #
b10000000000000000000000000110000 C
b110000 =
b110000 R
b10 A
1"
#860
0"
#865
b11111111111100011111000011000010 ,
b10001100001000011111000000000000 *
b11111111111111111111000011010110 .
b11111111111111111111100011010110 +
b11111111111111111111100011000010 -
b10 &
b11 '
b1000110 0
b111 1
b110110 )
b10001100001000011111101100110110 /
b10001100001000011111101100110110 T
b100 A
b1010111 #
1"
#870
0"
#875
b1011000 #
b111 <
b111 K
b10110 ?
b1000 A
1"
#880
0"
#885
13
b10000 A
b1011001 #
1"
#890
0"
#895
b1011010 #
b100000 A
1"
#900
0"
#905
b1000000 A
b1011011 #
1"
#910
0"
#915
b1011100 #
b10000000000000000000000000110100 >
b1 A
1"
#920
0"
#925
b10000000000000000000000000110100 C
b110100 =
b110100 R
b10 A
b1011101 #
1"
#930
0"
#935
b11111111111100000011010101000100 ,
b11010100010000000011000000000000 *
b11111111111111111111110101000010 .
b11111111111111111111110101000011 +
b11111111111111111111110101000100 -
b100 &
b0 '
b1101010 0
b11 1
b1000 )
b1011110 #
b100 A
b11010100010000000011000110001000 /
b11010100010000000011000110001000 T
1"
#940
0"
#945
b11 <
b11 K
b11 ?
b1000 A
b1011111 #
1"
#950
0"
#955
b1100000 #
b10000 A
1"
#960
0"
#965
b100000 A
b1100001 #
1"
#970
0"
#975
b1100010 #
b1000000 A
1"
#980
0"
#985
b10000000000000000000000000111000 >
b1 A
b1100011 #
1"
#990
0"
#995
b1100100 #
b10000000000000000000000000111000 C
b111000 =
b111000 R
b10 A
1"
#1000
0"
#1005
b11111111111101001011100011110000 ,
b10001111000101001011000000000000 *
b11111111111111111111000011111010 .
b11111111111111111111100011111010 +
b11111111111111111111100011110001 -
b10001 &
b1001 '
b1000111 0
b1111 )
b10001111000101001011110100001111 /
b10001111000101001011110100001111 T
b100 A
b1100101 #
1"
#1010
0"
#1015
b1100110 #
b11010 ?
b1000 A
1"
#1020
0"
#1025
b10000 A
b1100111 #
1"
#1030
0"
#1035
b1101000 #
b100000 A
1"
#1040
0"
#1045
b1000000 A
b1101001 #
1"
#1050
0"
#1055
b1101010 #
b10000000000000000000000000111100 >
b1 A
1"
#1060
0"
#1065
b10000000000000000000000000111100 C
b111100 =
b111100 R
b10 A
b1101011 #
1"
#1070
0"
#1075
b11111010111100110100 ,
b1110011010111111010000000000000 *
b111100110110 .
b11100110111 +
b11100110101 -
b10101 &
b11111 '
b111001 0
b10 1
b11 )
b1101100 #
b100 A
b1110011010111111010101110000011 /
b1110011010111111010101110000011 T
1"
#1080
0"
#1085
18
1@
b11100110101 5
b11100110101 I
b10 <
b10 K
b10111 ?
b1000 A
b1101101 #
1"
#1090
0"
#1095
b1101110 #
18
1@
b10000 A
b11100110101 (
b11100110101 J
1"
#1100
0"
#1105
18
1@
b100000 A
b1101111 #
1"
#1110
0"
#1115
b100001011000100100010101110001 O
b1110000 #
b11100110101 7
b11100110101 N
18
1@
b1000000 A
1"
#1120
0"
#1125
b1000010110001001000101 2
b1000010110001001000101 S
b10000000000000000000000001000000 >
18
1@
b1 A
b1110001 #
1"
#1130
0"
#1135
b1110010 #
18
1@
b10000000000000000000000001000000 C
b1000000 =
b1000000 R
b10 A
1"
#1140
0"
#1145
b11111111111101000100100101010000 ,
b10010101000101000100000000000000 *
b11111111111111111111100101011100 .
b11111111111111111111100101011101 +
b11111111111111111111100101010001 -
b10001 &
b1000 '
b1001010 0
b100 1
b110100 )
b10010101000101000100111010110100 /
b10010101000101000100111010110100 T
18
1@
b100 A
b1110011 #
1"
#1150
0"
#1155
b1110100 #
08
0@
b100 <
b100 K
b11101 ?
b1000 A
1"
#1160
0"
#1165
03
b10000 A
b1110101 #
1"
#1170
0"
#1175
b1110110 #
b100000 A
1"
#1180
0"
#1185
b1000000 A
b1110111 #
1"
#1190
0"
#1195
b1111000 #
b10000000000000000000000001000100 >
b1 A
1"
#1200
0"
#1205
b10000000000000000000000001000100 C
b1000100 =
b1000100 R
b10 A
b1111001 #
1"
#1210
0"
#1215
b11111111111100101001100000111010 ,
b10000011101100101001000000000000 *
b11111111111111111111000000101110 .
b11111111111111111111100000101110 +
b11111111111111111111100000111011 -
b11011 &
b101 '
b1000001 0
b1 1
b1101110 )
b1111010 #
b100 A
b10000011101100101001011101101110 /
b10000011101100101001011101101110 T
1"
#1220
0"
#1225
b1 <
b1 K
b1110 ?
b1001101011001010000000000000000 D
b1001101011001010000000000000000 L
b1000 A
b1111011 #
1"
#1230
0"
#1235
b1111100 #
b1001101011001010000000000000000 6
b1001101011001010000000000000000 H
b10000 A
13
1"
#1240
0"
#1245
b1001101011001010000011100110101 (
b1001101011001010000011100110101 J
b100000 A
b1111101 #
1"
#1250
0"
#1255
b1111110 #
b1000000 A
1"
#1260
0"
#1265
b10000000000000000000000001001000 >
b1 A
b1111111 #
1"
#1270
0"
#1275
b10000000 #
b10000000000000000000000001001000 C
b1001000 =
b1001000 R
b10 A
1"
#1280
0"
#1285
b11111111111111001011111100110000 ,
b11110011000111001011000000000000 *
b11111111111111111111111100110110 .
b11111111111111111111111100110111 +
b11111111111111111111111100110001 -
b10001 &
b11001 '
b1111001 0
b11 1
b1001011 )
b11110011000111001011101111001011 /
b11110011000111001011101111001011 T
b100 A
b10000001 #
1"
#1290
0"
#1295
b10000010 #
b11 <
b11 K
b10111 ?
b0 D
b0 L
b1000 A
1"
#1300
0"
#1305
b0 6
b0 H
b10000 A
b10000011 #
1"
#1310
0"
#1315
b10000100 #
b100000 A
b11100110101 (
b11100110101 J
1"
#1320
0"
#1325
b1000000 A
b10000101 #
1"
#1330
0"
#1335
b10000110 #
b10000000000000000000000001001100 >
b1 A
1"
#1340
0"
#1345
b10000000000000000000000001001100 C
b1001100 =
b1001100 R
b10 A
b10000111 #
1"
#1350
0"
